{
  "generatedAt": "2026-04-13T08:13:33+00:00",
  "snapshotDate": "2026-04-13",
  "rows": 100,
  "data": [
    {
      "tconst": "tt12042730",
      "primaryTitle": "Project Hail Mary",
      "titleType": "movie",
      "startYear": 2026,
      "genres": "Adventure,Comedy,Sci-Fi",
      "numVotesCurrent": 163542,
      "numVotesPrevious": 142946,
      "deltaVotes": 20596,
      "pctChange": 14.41
    },
    {
      "tconst": "tt28650488",
      "primaryTitle": "The Super Mario Galaxy Movie",
      "titleType": "movie",
      "startYear": 2026,
      "genres": "Adventure,Animation,Comedy",
      "numVotesCurrent": 19998,
      "numVotesPrevious": 10226,
      "deltaVotes": 9772,
      "pctChange": 95.56
    },
    {
      "tconst": "tt32430579",
      "primaryTitle": "Crime 101",
      "titleType": "movie",
      "startYear": 2026,
      "genres": "Crime,Drama,Thriller",
      "numVotesCurrent": 43044,
      "numVotesPrevious": 33506,
      "deltaVotes": 9538,
      "pctChange": 28.47
    },
    {
      "tconst": "tt33071426",
      "primaryTitle": "The Drama",
      "titleType": "movie",
      "startYear": 2026,
      "genres": "Comedy,Drama,Romance",
      "numVotesCurrent": 10652,
      "numVotesPrevious": 4012,
      "deltaVotes": 6640,
      "pctChange": 165.5
    },
    {
      "tconst": "tt8036976",
      "primaryTitle": "Send Help",
      "titleType": "movie",
      "startYear": 2026,
      "genres": "Adventure,Horror,Thriller",
      "numVotesCurrent": 64601,
      "numVotesPrevious": 60365,
      "deltaVotes": 4236,
      "pctChange": 7.02
    },
    {
      "tconst": "tt15574124",
      "primaryTitle": "Peaky Blinders: The Immortal Man",
      "titleType": "movie",
      "startYear": 2026,
      "genres": "Crime,Drama,History",
      "numVotesCurrent": 61798,
      "numVotesPrevious": 57820,
      "deltaVotes": 3978,
      "pctChange": 6.88
    },
    {
      "tconst": "tt32937780",
      "primaryTitle": "Something Very Bad Is Going to Happen",
      "titleType": "tvMiniSeries",
      "startYear": 2026,
      "genres": "Drama,Horror",
      "numVotesCurrent": 13971,
      "numVotesPrevious": 10024,
      "deltaVotes": 3947,
      "pctChange": 39.38
    },
    {
      "tconst": "tt1757678",
      "primaryTitle": "Avatar: Fire and Ash",
      "titleType": "movie",
      "startYear": 2025,
      "genres": "Action,Adventure,Animation",
      "numVotesCurrent": 148021,
      "numVotesPrevious": 144082,
      "deltaVotes": 3939,
      "pctChange": 2.73
    },
    {
      "tconst": "tt30144839",
      "primaryTitle": "One Battle After Another",
      "titleType": "movie",
      "startYear": 2025,
      "genres": "Action,Crime,Drama",
      "numVotesCurrent": 383981,
      "numVotesPrevious": 380109,
      "deltaVotes": 3872,
      "pctChange": 1.02
    },
    {
      "tconst": "tt33244668",
      "primaryTitle": "Anaconda",
      "titleType": "movie",
      "startYear": 2025,
      "genres": "Action,Adventure,Comedy",
      "numVotesCurrent": 50538,
      "numVotesPrevious": 46748,
      "deltaVotes": 3790,
      "pctChange": 8.11
    },
    {
      "tconst": "tt31193180",
      "primaryTitle": "Sinners",
      "titleType": "movie",
      "startYear": 2025,
      "genres": "Action,Drama,Horror",
      "numVotesCurrent": 458656,
      "numVotesPrevious": 455479,
      "deltaVotes": 3177,
      "pctChange": 0.7
    },
    {
      "tconst": "tt31050594",
      "primaryTitle": "Mercy",
      "titleType": "movie",
      "startYear": 2026,
      "genres": "Action,Crime,Drama",
      "numVotesCurrent": 50830,
      "numVotesPrevious": 47717,
      "deltaVotes": 3113,
      "pctChange": 6.52
    },
    {
      "tconst": "tt27543632",
      "primaryTitle": "The Housemaid",
      "titleType": "movie",
      "startYear": 2025,
      "genres": "Drama,Mystery,Thriller",
      "numVotesCurrent": 126705,
      "numVotesPrevious": 123708,
      "deltaVotes": 2997,
      "pctChange": 2.42
    },
    {
      "tconst": "tt31810018",
      "primaryTitle": "Detective Hole",
      "titleType": "tvSeries",
      "startYear": 2026,
      "genres": "Crime,Drama,Mystery",
      "numVotesCurrent": 10895,
      "numVotesPrevious": 7906,
      "deltaVotes": 2989,
      "pctChange": 37.81
    },
    {
      "tconst": "tt15940132",
      "primaryTitle": "War Machine",
      "titleType": "movie",
      "startYear": 2026,
      "genres": "Action,Sci-Fi,Thriller",
      "numVotesCurrent": 81677,
      "numVotesPrevious": 78987,
      "deltaVotes": 2690,
      "pctChange": 3.41
    },
    {
      "tconst": "tt32141377",
      "primaryTitle": "28 Years Later: The Bone Temple",
      "titleType": "movie",
      "startYear": 2026,
      "genres": "Horror,Sci-Fi,Thriller",
      "numVotesCurrent": 79556,
      "numVotesPrevious": 76960,
      "deltaVotes": 2596,
      "pctChange": 3.37
    },
    {
      "tconst": "tt32916440",
      "primaryTitle": "Marty Supreme",
      "titleType": "movie",
      "startYear": 2025,
      "genres": "Drama,Sport",
      "numVotesCurrent": 151506,
      "numVotesPrevious": 149016,
      "deltaVotes": 2490,
      "pctChange": 1.67
    },
    {
      "tconst": "tt0816692",
      "primaryTitle": "Interstellar",
      "titleType": "movie",
      "startYear": 2014,
      "genres": "Adventure,Drama,Sci-Fi",
      "numVotesCurrent": 2509529,
      "numVotesPrevious": 2507039,
      "deltaVotes": 2490,
      "pctChange": 0.1
    },
    {
      "tconst": "tt27552099",
      "primaryTitle": "Mike & Nick & Nick & Alice",
      "titleType": "movie",
      "startYear": 2026,
      "genres": "Action,Comedy,Crime",
      "numVotesCurrent": 10877,
      "numVotesPrevious": 8411,
      "deltaVotes": 2466,
      "pctChange": 29.32
    },
    {
      "tconst": "tt26443597",
      "primaryTitle": "Zootopia 2",
      "titleType": "movie",
      "startYear": 2025,
      "genres": "Action,Adventure,Animation",
      "numVotesCurrent": 120210,
      "numVotesPrevious": 117817,
      "deltaVotes": 2393,
      "pctChange": 2.03
    },
    {
      "tconst": "tt26443616",
      "primaryTitle": "Hoppers",
      "titleType": "movie",
      "startYear": 2026,
      "genres": "Adventure,Animation,Comedy",
      "numVotesCurrent": 29763,
      "numVotesPrevious": 27431,
      "deltaVotes": 2332,
      "pctChange": 8.5
    },
    {
      "tconst": "tt26581740",
      "primaryTitle": "Weapons",
      "titleType": "movie",
      "startYear": 2025,
      "genres": "Horror,Mystery",
      "numVotesCurrent": 338855,
      "numVotesPrevious": 336812,
      "deltaVotes": 2043,
      "pctChange": 0.61
    },
    {
      "tconst": "tt39139925",
      "primaryTitle": "Dhurandhar The Revenge",
      "titleType": "movie",
      "startYear": 2026,
      "genres": "Action,Crime,Thriller",
      "numVotesCurrent": 41911,
      "numVotesPrevious": 39891,
      "deltaVotes": 2020,
      "pctChange": 5.06
    },
    {
      "tconst": "tt27497448",
      "primaryTitle": "A Knight of the Seven Kingdoms",
      "titleType": "tvSeries",
      "startYear": 2026,
      "genres": "Action,Adventure,Drama",
      "numVotesCurrent": 225200,
      "numVotesPrevious": 223228,
      "deltaVotes": 1972,
      "pctChange": 0.88
    },
    {
      "tconst": "tt27047903",
      "primaryTitle": "Scream 7",
      "titleType": "movie",
      "startYear": 2026,
      "genres": "Horror,Mystery",
      "numVotesCurrent": 43186,
      "numVotesPrevious": 41288,
      "deltaVotes": 1898,
      "pctChange": 4.6
    },
    {
      "tconst": "tt0903747",
      "primaryTitle": "Breaking Bad",
      "titleType": "tvSeries",
      "startYear": 2008,
      "genres": "Crime,Drama,Thriller",
      "numVotesCurrent": 2596925,
      "numVotesPrevious": 2595048,
      "deltaVotes": 1877,
      "pctChange": 0.07
    },
    {
      "tconst": "tt16311594",
      "primaryTitle": "F1: The Movie",
      "titleType": "movie",
      "startYear": 2025,
      "genres": "Action,Drama,Sport",
      "numVotesCurrent": 345764,
      "numVotesPrevious": 343926,
      "deltaVotes": 1838,
      "pctChange": 0.53
    },
    {
      "tconst": "tt32897959",
      "primaryTitle": "Wuthering Heights",
      "titleType": "movie",
      "startYear": 2026,
      "genres": "Drama,Romance",
      "numVotesCurrent": 54078,
      "numVotesPrevious": 52256,
      "deltaVotes": 1822,
      "pctChange": 3.49
    },
    {
      "tconst": "tt1341338",
      "primaryTitle": "Good Luck, Have Fun, Don't Die",
      "titleType": "movie",
      "startYear": 2025,
      "genres": "Action,Adventure,Comedy",
      "numVotesCurrent": 33339,
      "numVotesPrevious": 31573,
      "deltaVotes": 1766,
      "pctChange": 5.59
    },
    {
      "tconst": "tt14905854",
      "primaryTitle": "Hamnet",
      "titleType": "movie",
      "startYear": 2025,
      "genres": "Biography,Drama,History",
      "numVotesCurrent": 102550,
      "numVotesPrevious": 100904,
      "deltaVotes": 1646,
      "pctChange": 1.63
    },
    {
      "tconst": "tt0468569",
      "primaryTitle": "The Dark Knight",
      "titleType": "movie",
      "startYear": 2008,
      "genres": "Action,Crime,Drama",
      "numVotesCurrent": 3155324,
      "numVotesPrevious": 3153699,
      "deltaVotes": 1625,
      "pctChange": 0.05
    },
    {
      "tconst": "tt31938062",
      "primaryTitle": "The Pitt",
      "titleType": "tvSeries",
      "startYear": 2025,
      "genres": "Drama",
      "numVotesCurrent": 132140,
      "numVotesPrevious": 130544,
      "deltaVotes": 1596,
      "pctChange": 1.22
    },
    {
      "tconst": "tt12300742",
      "primaryTitle": "Bugonia",
      "titleType": "movie",
      "startYear": 2025,
      "genres": "Comedy,Crime,Sci-Fi",
      "numVotesCurrent": 173888,
      "numVotesPrevious": 172308,
      "deltaVotes": 1580,
      "pctChange": 0.92
    },
    {
      "tconst": "tt1312221",
      "primaryTitle": "Frankenstein",
      "titleType": "movie",
      "startYear": 2025,
      "genres": "Drama,Fantasy,Horror",
      "numVotesCurrent": 300960,
      "numVotesPrevious": 299384,
      "deltaVotes": 1576,
      "pctChange": 0.53
    },
    {
      "tconst": "tt14364480",
      "primaryTitle": "Wake Up Dead Man",
      "titleType": "movie",
      "startYear": 2025,
      "genres": "Comedy,Crime,Drama",
      "numVotesCurrent": 229165,
      "numVotesPrevious": 227600,
      "deltaVotes": 1565,
      "pctChange": 0.69
    },
    {
      "tconst": "tt31514146",
      "primaryTitle": "I Swear",
      "titleType": "movie",
      "startYear": 2025,
      "genres": "Biography,Drama",
      "numVotesCurrent": 34013,
      "numVotesPrevious": 32474,
      "deltaVotes": 1539,
      "pctChange": 4.74
    },
    {
      "tconst": "tt1375666",
      "primaryTitle": "Inception",
      "titleType": "movie",
      "startYear": 2010,
      "genres": "Action,Adventure,Sci-Fi",
      "numVotesCurrent": 2804960,
      "numVotesPrevious": 2803437,
      "deltaVotes": 1523,
      "pctChange": 0.05
    },
    {
      "tconst": "tt6741278",
      "primaryTitle": "Invincible",
      "titleType": "tvSeries",
      "startYear": 2021,
      "genres": "Action,Adventure,Animation",
      "numVotesCurrent": 318007,
      "numVotesPrevious": 316498,
      "deltaVotes": 1509,
      "pctChange": 0.48
    },
    {
      "tconst": "tt0137523",
      "primaryTitle": "Fight Club",
      "titleType": "movie",
      "startYear": 1999,
      "genres": "Crime,Drama,Thriller",
      "numVotesCurrent": 2593969,
      "numVotesPrevious": 2592463,
      "deltaVotes": 1506,
      "pctChange": 0.06
    },
    {
      "tconst": "tt29567915",
      "primaryTitle": "Nuremberg",
      "titleType": "movie",
      "startYear": 2025,
      "genres": "Biography,Drama,History",
      "numVotesCurrent": 81002,
      "numVotesPrevious": 79529,
      "deltaVotes": 1473,
      "pctChange": 1.85
    },
    {
      "tconst": "tt4357198",
      "primaryTitle": "How to Make a Killing",
      "titleType": "movie",
      "startYear": 2026,
      "genres": "Comedy,Drama,Thriller",
      "numVotesCurrent": 15034,
      "numVotesPrevious": 13563,
      "deltaVotes": 1471,
      "pctChange": 10.85
    },
    {
      "tconst": "tt15239678",
      "primaryTitle": "Dune: Part Two",
      "titleType": "movie",
      "startYear": 2024,
      "genres": "Action,Adventure,Drama",
      "numVotesCurrent": 731751,
      "numVotesPrevious": 730293,
      "deltaVotes": 1458,
      "pctChange": 0.2
    },
    {
      "tconst": "tt6718170",
      "primaryTitle": "The Super Mario Bros. Movie",
      "titleType": "movie",
      "startYear": 2023,
      "genres": "Adventure,Animation,Comedy",
      "numVotesCurrent": 289485,
      "numVotesPrevious": 288032,
      "deltaVotes": 1453,
      "pctChange": 0.5
    },
    {
      "tconst": "tt5950044",
      "primaryTitle": "Superman",
      "titleType": "movie",
      "startYear": 2025,
      "genres": "Action,Adventure,Sci-Fi",
      "numVotesCurrent": 403268,
      "numVotesPrevious": 401878,
      "deltaVotes": 1390,
      "pctChange": 0.35
    },
    {
      "tconst": "tt0111161",
      "primaryTitle": "The Shawshank Redemption",
      "titleType": "movie",
      "startYear": 1994,
      "genres": "Drama",
      "numVotesCurrent": 3175959,
      "numVotesPrevious": 3174612,
      "deltaVotes": 1347,
      "pctChange": 0.04
    },
    {
      "tconst": "tt31227572",
      "primaryTitle": "Predator: Badlands",
      "titleType": "movie",
      "startYear": 2025,
      "genres": "Action,Adventure,Sci-Fi",
      "numVotesCurrent": 140468,
      "numVotesPrevious": 139147,
      "deltaVotes": 1321,
      "pctChange": 0.95
    },
    {
      "tconst": "tt0993846",
      "primaryTitle": "The Wolf of Wall Street",
      "titleType": "movie",
      "startYear": 2013,
      "genres": "Biography,Comedy,Crime",
      "numVotesCurrent": 1778531,
      "numVotesPrevious": 1777211,
      "deltaVotes": 1320,
      "pctChange": 0.07
    },
    {
      "tconst": "tt0944947",
      "primaryTitle": "Game of Thrones",
      "titleType": "tvSeries",
      "startYear": 2011,
      "genres": "Action,Adventure,Drama",
      "numVotesCurrent": 2602061,
      "numVotesPrevious": 2600785,
      "deltaVotes": 1276,
      "pctChange": 0.05
    },
    {
      "tconst": "tt0109830",
      "primaryTitle": "Forrest Gump",
      "titleType": "movie",
      "startYear": 1994,
      "genres": "Drama,Romance",
      "numVotesCurrent": 2486733,
      "numVotesPrevious": 2485460,
      "deltaVotes": 1273,
      "pctChange": 0.05
    },
    {
      "tconst": "tt15398776",
      "primaryTitle": "Oppenheimer",
      "titleType": "movie",
      "startYear": 2023,
      "genres": "Biography,Drama,History",
      "numVotesCurrent": 1018675,
      "numVotesPrevious": 1017455,
      "deltaVotes": 1220,
      "pctChange": 0.12
    },
    {
      "tconst": "tt33978029",
      "primaryTitle": "Ready or Not 2: Here I Come",
      "titleType": "movie",
      "startYear": 2026,
      "genres": "Comedy,Horror,Thriller",
      "numVotesCurrent": 11704,
      "numVotesPrevious": 10502,
      "deltaVotes": 1202,
      "pctChange": 11.45
    },
    {
      "tconst": "tt1160419",
      "primaryTitle": "Dune: Part One",
      "titleType": "movie",
      "startYear": 2021,
      "genres": "Action,Adventure,Drama",
      "numVotesCurrent": 1035284,
      "numVotesPrevious": 1034136,
      "deltaVotes": 1148,
      "pctChange": 0.11
    },
    {
      "tconst": "tt7798634",
      "primaryTitle": "Ready or Not",
      "titleType": "movie",
      "startYear": 2019,
      "genres": "Action,Comedy,Horror",
      "numVotesCurrent": 240502,
      "numVotesPrevious": 239373,
      "deltaVotes": 1129,
      "pctChange": 0.47
    },
    {
      "tconst": "tt27714581",
      "primaryTitle": "Sentimental Value",
      "titleType": "movie",
      "startYear": 2025,
      "genres": "Drama",
      "numVotesCurrent": 70781,
      "numVotesPrevious": 69662,
      "deltaVotes": 1119,
      "pctChange": 1.61
    },
    {
      "tconst": "tt33204276",
      "primaryTitle": "The Madison",
      "titleType": "tvSeries",
      "startYear": 2026,
      "genres": "Action,Drama",
      "numVotesCurrent": 11258,
      "numVotesPrevious": 10180,
      "deltaVotes": 1078,
      "pctChange": 10.59
    },
    {
      "tconst": "tt27444205",
      "primaryTitle": "Paradise",
      "titleType": "tvSeries",
      "startYear": 2025,
      "genres": "Action,Drama,Thriller",
      "numVotesCurrent": 73456,
      "numVotesPrevious": 72389,
      "deltaVotes": 1067,
      "pctChange": 1.47
    },
    {
      "tconst": "tt0264464",
      "primaryTitle": "Catch Me If You Can",
      "titleType": "movie",
      "startYear": 2002,
      "genres": "Biography,Crime,Drama",
      "numVotesCurrent": 1231100,
      "numVotesPrevious": 1230055,
      "deltaVotes": 1045,
      "pctChange": 0.08
    },
    {
      "tconst": "tt0114369",
      "primaryTitle": "Seven",
      "titleType": "movie",
      "startYear": 1995,
      "genres": "Crime,Drama,Mystery",
      "numVotesCurrent": 2012339,
      "numVotesPrevious": 2011296,
      "deltaVotes": 1043,
      "pctChange": 0.05
    },
    {
      "tconst": "tt0335345",
      "primaryTitle": "The Passion of the Christ",
      "titleType": "movie",
      "startYear": 2004,
      "genres": "Drama",
      "numVotesCurrent": 272407,
      "numVotesPrevious": 271376,
      "deltaVotes": 1031,
      "pctChange": 0.38
    },
    {
      "tconst": "tt8599532",
      "primaryTitle": "Young Sherlock",
      "titleType": "tvSeries",
      "startYear": 2026,
      "genres": "Action,Adventure,Mystery",
      "numVotesCurrent": 22637,
      "numVotesPrevious": 21618,
      "deltaVotes": 1019,
      "pctChange": 4.71
    },
    {
      "tconst": "tt0133093",
      "primaryTitle": "The Matrix",
      "titleType": "movie",
      "startYear": 1999,
      "genres": "Action,Sci-Fi",
      "numVotesCurrent": 2239074,
      "numVotesPrevious": 2238067,
      "deltaVotes": 1007,
      "pctChange": 0.04
    },
    {
      "tconst": "tt0120737",
      "primaryTitle": "The Lord of the Rings: The Fellowship of the Ring",
      "titleType": "movie",
      "startYear": 2001,
      "genres": "Adventure,Drama,Fantasy",
      "numVotesCurrent": 2199062,
      "numVotesPrevious": 2198062,
      "deltaVotes": 1000,
      "pctChange": 0.05
    },
    {
      "tconst": "tt27613895",
      "primaryTitle": "GOAT",
      "titleType": "movie",
      "startYear": 2026,
      "genres": "Action,Adventure,Animation",
      "numVotesCurrent": 13319,
      "numVotesPrevious": 12323,
      "deltaVotes": 996,
      "pctChange": 8.08
    },
    {
      "tconst": "tt1130884",
      "primaryTitle": "Shutter Island",
      "titleType": "movie",
      "startYear": 2010,
      "genres": "Drama,Mystery,Thriller",
      "numVotesCurrent": 1638099,
      "numVotesPrevious": 1637133,
      "deltaVotes": 966,
      "pctChange": 0.06
    },
    {
      "tconst": "tt3659388",
      "primaryTitle": "The Martian",
      "titleType": "movie",
      "startYear": 2015,
      "genres": "Adventure,Drama,Sci-Fi",
      "numVotesCurrent": 1006563,
      "numVotesPrevious": 1005609,
      "deltaVotes": 954,
      "pctChange": 0.09
    },
    {
      "tconst": "tt7286456",
      "primaryTitle": "Joker",
      "titleType": "movie",
      "startYear": 2019,
      "genres": "Crime,Drama,Thriller",
      "numVotesCurrent": 1686021,
      "numVotesPrevious": 1685071,
      "deltaVotes": 950,
      "pctChange": 0.06
    },
    {
      "tconst": "tt4154796",
      "primaryTitle": "Avengers: Endgame",
      "titleType": "movie",
      "startYear": 2019,
      "genres": "Action,Adventure,Sci-Fi",
      "numVotesCurrent": 1438346,
      "numVotesPrevious": 1437399,
      "deltaVotes": 947,
      "pctChange": 0.07
    },
    {
      "tconst": "tt4574334",
      "primaryTitle": "Stranger Things",
      "titleType": "tvSeries",
      "startYear": 2016,
      "genres": "Drama,Fantasy,Horror",
      "numVotesCurrent": 1688448,
      "numVotesPrevious": 1687501,
      "deltaVotes": 947,
      "pctChange": 0.06
    },
    {
      "tconst": "tt6751668",
      "primaryTitle": "Parasite",
      "titleType": "movie",
      "startYear": 2019,
      "genres": "Drama,Thriller",
      "numVotesCurrent": 1156139,
      "numVotesPrevious": 1155197,
      "deltaVotes": 942,
      "pctChange": 0.08
    },
    {
      "tconst": "tt0110912",
      "primaryTitle": "Pulp Fiction",
      "titleType": "movie",
      "startYear": 1994,
      "genres": "Crime,Drama",
      "numVotesCurrent": 2426800,
      "numVotesPrevious": 2425859,
      "deltaVotes": 941,
      "pctChange": 0.04
    },
    {
      "tconst": "tt33014583",
      "primaryTitle": "Dhurandhar",
      "titleType": "movie",
      "startYear": 2025,
      "genres": "Action,Adventure,Crime",
      "numVotesCurrent": 133673,
      "numVotesPrevious": 132737,
      "deltaVotes": 936,
      "pctChange": 0.71
    },
    {
      "tconst": "tt0172495",
      "primaryTitle": "Gladiator",
      "titleType": "movie",
      "startYear": 2000,
      "genres": "Action,Adventure,Drama",
      "numVotesCurrent": 1842093,
      "numVotesPrevious": 1841168,
      "deltaVotes": 925,
      "pctChange": 0.05
    },
    {
      "tconst": "tt4154756",
      "primaryTitle": "Avengers: Infinity War",
      "titleType": "movie",
      "startYear": 2018,
      "genres": "Action,Adventure,Sci-Fi",
      "numVotesCurrent": 1364750,
      "numVotesPrevious": 1363831,
      "deltaVotes": 919,
      "pctChange": 0.07
    },
    {
      "tconst": "tt10872600",
      "primaryTitle": "Spider-Man: No Way Home",
      "titleType": "movie",
      "startYear": 2021,
      "genres": "Action,Adventure,Fantasy",
      "numVotesCurrent": 1013538,
      "numVotesPrevious": 1012620,
      "deltaVotes": 918,
      "pctChange": 0.09
    },
    {
      "tconst": "tt32642706",
      "primaryTitle": "The Rip",
      "titleType": "movie",
      "startYear": 2026,
      "genres": "Action,Crime,Drama",
      "numVotesCurrent": 120783,
      "numVotesPrevious": 119868,
      "deltaVotes": 915,
      "pctChange": 0.76
    },
    {
      "tconst": "tt10374610",
      "primaryTitle": "The Long Walk",
      "titleType": "movie",
      "startYear": 2025,
      "genres": "Horror,Thriller",
      "numVotesCurrent": 108700,
      "numVotesPrevious": 107802,
      "deltaVotes": 898,
      "pctChange": 0.83
    },
    {
      "tconst": "tt0120382",
      "primaryTitle": "The Truman Show",
      "titleType": "movie",
      "startYear": 1998,
      "genres": "Comedy,Drama",
      "numVotesCurrent": 1365679,
      "numVotesPrevious": 1364781,
      "deltaVotes": 898,
      "pctChange": 0.07
    },
    {
      "tconst": "tt29768334",
      "primaryTitle": "Train Dreams",
      "titleType": "movie",
      "startYear": 2025,
      "genres": "Drama",
      "numVotesCurrent": 99832,
      "numVotesPrevious": 98938,
      "deltaVotes": 894,
      "pctChange": 0.9
    },
    {
      "tconst": "tt0102926",
      "primaryTitle": "The Silence of the Lambs",
      "titleType": "movie",
      "startYear": 1991,
      "genres": "Crime,Drama,Horror",
      "numVotesCurrent": 1716264,
      "numVotesPrevious": 1715372,
      "deltaVotes": 892,
      "pctChange": 0.05
    },
    {
      "tconst": "tt10548174",
      "primaryTitle": "28 Years Later",
      "titleType": "movie",
      "startYear": 2025,
      "genres": "Horror,Sci-Fi,Thriller",
      "numVotesCurrent": 207327,
      "numVotesPrevious": 206435,
      "deltaVotes": 892,
      "pctChange": 0.43
    },
    {
      "tconst": "tt7181546",
      "primaryTitle": "Ballerina",
      "titleType": "movie",
      "startYear": 2025,
      "genres": "Action,Thriller",
      "numVotesCurrent": 146775,
      "numVotesPrevious": 145891,
      "deltaVotes": 884,
      "pctChange": 0.61
    },
    {
      "tconst": "tt0361748",
      "primaryTitle": "Inglourious Basterds",
      "titleType": "movie",
      "startYear": 2009,
      "genres": "Adventure,Drama,War",
      "numVotesCurrent": 1775462,
      "numVotesPrevious": 1774585,
      "deltaVotes": 877,
      "pctChange": 0.05
    },
    {
      "tconst": "tt2560140",
      "primaryTitle": "Attack on Titan",
      "titleType": "tvSeries",
      "startYear": 2013,
      "genres": "Action,Adventure,Animation",
      "numVotesCurrent": 706491,
      "numVotesPrevious": 705616,
      "deltaVotes": 875,
      "pctChange": 0.12
    },
    {
      "tconst": "tt0167260",
      "primaryTitle": "The Lord of the Rings: The Return of the King",
      "titleType": "movie",
      "startYear": 2003,
      "genres": "Adventure,Drama,Fantasy",
      "numVotesCurrent": 2157436,
      "numVotesPrevious": 2156580,
      "deltaVotes": 856,
      "pctChange": 0.04
    },
    {
      "tconst": "tt0167261",
      "primaryTitle": "The Lord of the Rings: The Two Towers",
      "titleType": "movie",
      "startYear": 2002,
      "genres": "Adventure,Drama,Fantasy",
      "numVotesCurrent": 1950067,
      "numVotesPrevious": 1949216,
      "deltaVotes": 851,
      "pctChange": 0.04
    },
    {
      "tconst": "tt11737520",
      "primaryTitle": "One Piece",
      "titleType": "tvSeries",
      "startYear": 2023,
      "genres": "Action,Adventure,Comedy",
      "numVotesCurrent": 202821,
      "numVotesPrevious": 201979,
      "deltaVotes": 842,
      "pctChange": 0.42
    },
    {
      "tconst": "tt9603208",
      "primaryTitle": "Mission: Impossible - The Final Reckoning",
      "titleType": "movie",
      "startYear": 2025,
      "genres": "Action,Adventure,Thriller",
      "numVotesCurrent": 225153,
      "numVotesPrevious": 224317,
      "deltaVotes": 836,
      "pctChange": 0.37
    },
    {
      "tconst": "tt4627382",
      "primaryTitle": "Roofman",
      "titleType": "movie",
      "startYear": 2025,
      "genres": "Biography,Crime,Drama",
      "numVotesCurrent": 69152,
      "numVotesPrevious": 68325,
      "deltaVotes": 827,
      "pctChange": 1.21
    },
    {
      "tconst": "tt1853728",
      "primaryTitle": "Django Unchained",
      "titleType": "movie",
      "startYear": 2012,
      "genres": "Drama,Western",
      "numVotesCurrent": 1875629,
      "numVotesPrevious": 1874802,
      "deltaVotes": 827,
      "pctChange": 0.04
    },
    {
      "tconst": "tt1190634",
      "primaryTitle": "The Boys",
      "titleType": "tvSeries",
      "startYear": 2019,
      "genres": "Action,Comedy,Crime",
      "numVotesCurrent": 847308,
      "numVotesPrevious": 846493,
      "deltaVotes": 815,
      "pctChange": 0.1
    },
    {
      "tconst": "tt7366338",
      "primaryTitle": "Chernobyl",
      "titleType": "tvMiniSeries",
      "startYear": 2019,
      "genres": "Drama,History,Thriller",
      "numVotesCurrent": 1028389,
      "numVotesPrevious": 1027576,
      "deltaVotes": 813,
      "pctChange": 0.08
    },
    {
      "tconst": "tt22202452",
      "primaryTitle": "Pluribus",
      "titleType": "tvSeries",
      "startYear": 2025,
      "genres": "Drama,Sci-Fi",
      "numVotesCurrent": 144216,
      "numVotesPrevious": 143405,
      "deltaVotes": 811,
      "pctChange": 0.57
    },
    {
      "tconst": "tt0068646",
      "primaryTitle": "The Godfather",
      "titleType": "movie",
      "startYear": 1972,
      "genres": "Crime,Drama",
      "numVotesCurrent": 2218556,
      "numVotesPrevious": 2217758,
      "deltaVotes": 798,
      "pctChange": 0.04
    },
    {
      "tconst": "tt0482571",
      "primaryTitle": "The Prestige",
      "titleType": "movie",
      "startYear": 2006,
      "genres": "Drama,Mystery,Sci-Fi",
      "numVotesCurrent": 1581376,
      "numVotesPrevious": 1580579,
      "deltaVotes": 797,
      "pctChange": 0.05
    },
    {
      "tconst": "tt2582802",
      "primaryTitle": "Whiplash",
      "titleType": "movie",
      "startYear": 2014,
      "genres": "Drama,Music",
      "numVotesCurrent": 1148094,
      "numVotesPrevious": 1147302,
      "deltaVotes": 792,
      "pctChange": 0.07
    },
    {
      "tconst": "tt28996126",
      "primaryTitle": "Nobody 2",
      "titleType": "movie",
      "startYear": 2025,
      "genres": "Action,Comedy,Crime",
      "numVotesCurrent": 87236,
      "numVotesPrevious": 86450,
      "deltaVotes": 786,
      "pctChange": 0.91
    },
    {
      "tconst": "tt0088763",
      "primaryTitle": "Back to the Future",
      "titleType": "movie",
      "startYear": 1985,
      "genres": "Adventure,Comedy,Sci-Fi",
      "numVotesCurrent": 1447141,
      "numVotesPrevious": 1446355,
      "deltaVotes": 786,
      "pctChange": 0.05
    },
    {
      "tconst": "tt12343534",
      "primaryTitle": "Jujutsu Kaisen",
      "titleType": "tvSeries",
      "startYear": 2020,
      "genres": "Action,Adventure,Animation",
      "numVotesCurrent": 201736,
      "numVotesPrevious": 200959,
      "deltaVotes": 777,
      "pctChange": 0.39
    },
    {
      "tconst": "tt3032476",
      "primaryTitle": "Better Call Saul",
      "titleType": "tvSeries",
      "startYear": 2015,
      "genres": "Crime,Drama",
      "numVotesCurrent": 827010,
      "numVotesPrevious": 826234,
      "deltaVotes": 776,
      "pctChange": 0.09
    },
    {
      "tconst": "tt14107334",
      "primaryTitle": "The Running Man",
      "titleType": "movie",
      "startYear": 2025,
      "genres": "Action,Adventure,Sci-Fi",
      "numVotesCurrent": 90881,
      "numVotesPrevious": 90109,
      "deltaVotes": 772,
      "pctChange": 0.86
    }
  ]
}